inte_visit_schedule/__init__.py
inte_visit_schedule/admin.py
inte_visit_schedule/apps.py
inte_visit_schedule/constants.py
inte_visit_schedule/models.py
inte_visit_schedule/migrations/__init__.py
inte_visit_schedule/tests/__init__.py
inte_visit_schedule/tests/test_schedule.py
inte_visit_schedule/tests/urls.py
inte_visit_schedule/visit_schedules/__init__.py
inte_visit_schedule/visit_schedules/crfs.py
inte_visit_schedule/visit_schedules/requisitions.py
inte_visit_schedule/visit_schedules/schedule.py
inte_visit_schedule/visit_schedules/visit_schedule.py
inte_visit_schedule-0.1.0.dist-info/AUTHORS
inte_visit_schedule-0.1.0.dist-info/LICENSE
inte_visit_schedule-0.1.0.dist-info/METADATA
inte_visit_schedule-0.1.0.dist-info/WHEEL
inte_visit_schedule-0.1.0.dist-info/top_level.txt
inte_visit_schedule-0.1.0.dist-info/RECORD
